Metadata-Version: 1.1
Name: django-comps
Version: 0.3.0
Summary: A simple application that provides an entry point for integrating front end designers into a django project
Home-page: https://github.com/caktus/django-comps
Author: Caktus Consulting Group
Author-email: solutions@caktusgroup.com
License: BSD
Platform: UNKNOWN
Classifier: Topic :: Internet :: WWW/HTTP :: Dynamic Content
Classifier: Intended Audience :: Developers
Classifier: License :: OSI Approved :: BSD License
Classifier: Programming Language :: Python
Classifier: Programming Language :: Python :: 2.6
Classifier: Programming Language :: Python :: 2.7
Classifier: Programming Language :: Python :: 3.3
Classifier: Framework :: Django
Classifier: Topic :: Software Development :: Libraries :: Python Modules
Classifier: Development Status :: 4 - Beta
Classifier: Operating System :: OS Independent
Classifier: Environment :: Web Environment
